Metadata-Version: 2.1
Name: Lotte
Version: 1.3.4
Summary: Lotte is a tool for quotation detection in texts and can deal with common properties of quotations, for example, ellipses or inaccurate quotations.
Home-page: https://pypi.org/project/quid/
Author: Frederik Arnold
Author-email: frederik.arnold@hu-berlin.de
License: UNKNOWN
Project-URL: Source, https://hu.berlin/quid
Keywords: quotation detection,literal citation extraction,key passages,natural language processing,nlp,text reuse
Platform: UNKNOWN
Classifier: Programming Language :: Python :: 3
Classifier: License :: OSI Approved :: Apache Software License
Classifier: Operating System :: OS Independent
Requires-Python: >=3.7
License-File: LICENSE
Requires-Dist: numpy (>=1.20.1)
Requires-Dist: yattag (>=1.14.0)
Requires-Dist: rapidfuzz (>=1.3.3)
Requires-Dist: datasketch (>=1.5.3)
